fabra/__init__.py
fabra/connection.py
fabra/destination.py
fabra/link_token.py
fabra/object.py
fabra/sdk.py
fabra/source.py
fabra/sync.py
fabra/models/__init__.py
fabra/models/operations/__init__.py
fabra/models/operations/create_destination.py
fabra/models/operations/create_link_token.py
fabra/models/operations/create_object.py
fabra/models/operations/create_source.py
fabra/models/operations/create_sync.py
fabra/models/operations/get_destinations.py
fabra/models/operations/get_namespaces.py
fabra/models/operations/get_objects.py
fabra/models/operations/get_schema.py
fabra/models/operations/get_sources.py
fabra/models/operations/get_syncs.py
fabra/models/operations/get_tables.py
fabra/models/shared/__init__.py
fabra/models/shared/bigqueryconfig.py
fabra/models/shared/columnschema.py
fabra/models/shared/connection.py
fabra/models/shared/connectiontype_enum.py
fabra/models/shared/createlinktokenrequest.py
fabra/models/shared/createlinktokenresponse.py
fabra/models/shared/destination.py
fabra/models/shared/destinationinput.py
fabra/models/shared/fieldmapping.py
fabra/models/shared/fieldtype_enum.py
fabra/models/shared/frequencyunits_enum.py
fabra/models/shared/mongodbconfig.py
fabra/models/shared/object.py
fabra/models/shared/objectfield.py
fabra/models/shared/objectinput.py
fabra/models/shared/redshiftconfig.py
fabra/models/shared/security.py
fabra/models/shared/snowflakeconfig.py
fabra/models/shared/source.py
fabra/models/shared/sourceinput.py
fabra/models/shared/sync.py
fabra/models/shared/syncinput.py
fabra/utils/__init__.py
fabra/utils/retries.py
fabra/utils/utils.py
fabra-0.5.2.dist-info/LICENSE
fabra-0.5.2.dist-info/METADATA
fabra-0.5.2.dist-info/WHEEL
fabra-0.5.2.dist-info/top_level.txt
fabra-0.5.2.dist-info/RECORD
